topylogic/__init__.py
topylogic/_topylogic.pyd
topylogic/_topylogic.so
topylogic/topylogic.py
topylogic-1.4.0.dist-info/LICENSE
topylogic-1.4.0.dist-info/METADATA
topylogic-1.4.0.dist-info/WHEEL
topylogic-1.4.0.dist-info/top_level.txt
topylogic-1.4.0.dist-info/RECORD
