Metadata-Version: 2.1
Name: topylogic
Version: 1.4.0
Summary: Context Free/Switching DFA/NFA library
Home-page: https://github.com/mstern98/topylogic-git
Author: Matthew Stern
Author-email: msstern98@gmail.com
License: UNKNOWN
Project-URL: Bug Tracker, https://github.com/mstern98/topylogic-git/issues
Platform: UNKNOWN
Classifier: Programming Language :: Python :: 3
Classifier: License :: OSI Approved :: MIT License
Classifier: Operating System :: OS Independent
Requires-Python: >=3.9
